<?xml version="1.0" encoding="UTF-8"?>
<!DOCTYPE struts PUBLIC
    "-//Apache Software Foundation//DTD Struts Configuration 2.5//EN"
    "http://struts.apache.org/dtds/struts-2.5.dtd">


<struts>

	<package name="registratin" extends="struts-default">
		
		<action name="user_registration" class="user.action.user_registration">
			<result name="input">/user_registration.jsp</result>
			<result name="success">/user_login.jsp</result>
		</action>
		
		<action name="company_registration" class="user.action.company_registration">
			<result name="input">/company_registration.jsp</result>
			<result name="success">/company_login.jsp</result>
		</action>
	</package>
	
	<package name="login" extends="struts-default">
		<action name="user_login" class="user.action.login" method="user_login">
			<result name="input">/user_login.jsp</result>
			<result name="success">/index.jsp</result>
		</action>
		<action name="company_login" class="user.action.login" method="company_login">
			<result name="input">/company_login.jsp</result>
			<result name="success">/index.jsp</result>
		</action>

	</package>
	
	<package name="user_logout" extends="struts-default">
		<action name="logout" class="user.action.logout">
			<result name="input">./index.jsp</result>
			<result name="success">./index.jsp</result>
		</action>
	</package>
	
	<package name="userinfo" extends="struts-default">
		<action name="AddBio" class="user.action.EditBio">
			<result name="input">./edit_bio.jsp</result>
			<result name="success">./index.jsp</result>
		</action>
		<action name="EditProfile" class="user.action.EditProfile">
			<result name="input">./edit_profile.jsp</result>
			<result name="success">./index.jsp</result>
		</action>
	</package>
	
	<package name="business" extends="struts-default">
		<action name="collection" class="user.action.CollectionWork">
			<result name="success">/collection.jsp</result>
		</action>
		<action name="addcollect" class="user.action.CollectionWork" method="addcollect">
			<result name="input">/index.jsp</result>
			<result name="success" type="chain">collection</result>
		</action>
		<action name="ListBio" class="user.action.ListBio">
			<result name="success">/userbio.jsp</result>
		</action>
		<action name="lookbio" class="user.action.EditBio" method="lookBio">
			<result name="input" type="chain">ListBio</result>
			<result name="success">/lookselfbio.jsp</result>
		</action>
		<action name="getbio" class="user.action.EditBio" method="searchbio">
			<result name="success">./lookselfbio.jsp</result>
		</action>
		<action name="editbio" class="user.action.EditBio" method="editbio">
			<result name="input" type="chain">ListBio</result>
			<result name="success" type="chain">ListBio</result>
		</action>
		<action name="delete" class="user.action.EditBio" method="delete">
			<result name="input" type="chain">ListBio</result>
			<result name="success" type="chain">ListBio</result>
		</action>
		<action name="deliver" class="user.action.DeliverBio">
			<result name="input">./index.jsp</result>
			<result name="success" type="redirect">/index.jsp</result>
		</action>
		
		<action name="getjobinfo" class="user.action.DeliverBio" method="getInfo">
			<result name="input">/index.jsp</result>
			<result name="success">/delivery.jsp</result>
		</action>
		
		<action name="getallinfo" class="user.action.DeliverBio" method="getAllWorkInfo">
			<result name="success">/delivery.jsp</result>
		</action>
		
		
		<action name="ListMessage" class="user.action.ListMessage">
			<result name="input">/index.jsp</result>
			<result name="success">/message.jsp</result>
		</action>
	</package>

</struts>